hsp_sdk/__init__.py
hsp_sdk/anthropic_hsp.py
hsp_sdk/aws_bedrock_hsp.py
hsp_sdk/azure_hsp.py
hsp_sdk/cli.py
hsp_sdk/openai_hsp.py
hsp_sdk/unified.py
hsp_protocol-0.2.0.dist-info/METADATA
hsp_protocol-0.2.0.dist-info/WHEEL
hsp_protocol-0.2.0.dist-info/entry_points.txt
hsp_protocol-0.2.0.dist-info/RECORD
