Metadata-Version: 2.4
Name: hsp-protocol
Version: 0.2.0
Summary: Human Supervision Protocol - Fail-closed AI governance for EU AI Act compliance
Project-URL: Homepage, https://hsp-protocol.com
Project-URL: Documentation, https://docs.hsp-protocol.com
Project-URL: Repository, https://github.com/hsp-protocol/hsp-sdk
Project-URL: Bug Tracker, https://github.com/hsp-protocol/hsp-sdk/issues
Project-URL: Patent Information, https://hsp-protocol.com/patent
Author-email: Jaqueline de Jesus <admin@hsp-protocol.com>
License: Proprietary - Licensed under PCT/US26/11908
Keywords: ai-governance,ai-safety,audit,blockchain,compliance,eu-ai-act,fail-closed,human-oversight,llm
Classifier: Development Status :: 4 - Beta
Classifier: Intended Audience :: Developers
Classifier: Intended Audience :: Financial and Insurance Industry
Classifier: Intended Audience :: Healthcare Industry
Classifier: Intended Audience :: Legal Industry
Classifier: License :: Other/Proprietary License
Classifier: Operating System :: OS Independent
Classifier: Programming Language :: Python :: 3
Classifier: Programming Language :: Python :: 3.9
Classifier: Programming Language :: Python :: 3.10
Classifier: Programming Language :: Python :: 3.11
Classifier: Programming Language :: Python :: 3.12
Classifier: Topic :: Scientific/Engineering :: Artificial Intelligence
Classifier: Topic :: Security :: Cryptography
Classifier: Topic :: System :: Logging
Requires-Python: >=3.9
Requires-Dist: httpx>=0.24.0
Provides-Extra: all
Requires-Dist: anthropic>=0.18.0; extra == 'all'
Requires-Dist: boto3>=1.28.0; extra == 'all'
Requires-Dist: google-generativeai>=0.3.0; extra == 'all'
Requires-Dist: openai>=1.0.0; extra == 'all'
Provides-Extra: anthropic
Requires-Dist: anthropic>=0.18.0; extra == 'anthropic'
Provides-Extra: bedrock
Requires-Dist: boto3>=1.28.0; extra == 'bedrock'
Provides-Extra: dev
Requires-Dist: black>=23.0.0; extra == 'dev'
Requires-Dist: mypy>=1.0.0; extra == 'dev'
Requires-Dist: pytest-asyncio>=0.21.0; extra == 'dev'
Requires-Dist: pytest>=7.0.0; extra == 'dev'
Requires-Dist: ruff>=0.1.0; extra == 'dev'
Provides-Extra: gemini
Requires-Dist: google-generativeai>=0.3.0; extra == 'gemini'
Provides-Extra: openai
Requires-Dist: openai>=1.0.0; extra == 'openai'
